redis_cache/__init__.py
redis_cache/cache_manager.py
Python_Redis_Caching-0.0.6.dist-info/METADATA
Python_Redis_Caching-0.0.6.dist-info/WHEEL
Python_Redis_Caching-0.0.6.dist-info/top_level.txt
Python_Redis_Caching-0.0.6.dist-info/RECORD
