Metadata-Version: 2.1
Name: Python-Redis-Caching
Version: 0.0.6
Summary: Caching your data to Redis
Home-page: https://github.com/nbmhoang/python-redis-caching
Author: Hoang Nguyen
Author-email: minhhoangnguyenbao99@gmail.com
License: UNKNOWN
Platform: UNKNOWN
Classifier: License :: OSI Approved :: MIT License
Classifier: Programming Language :: Python :: 3
Classifier: Programming Language :: Python :: 3.7
Classifier: Programming Language :: Python :: 3.8
Classifier: Programming Language :: Python :: 3.9
Requires-Python: >=3.6
Requires-Dist: redis
